setup.py
my_first_distributions/Binomialdistribution.py
my_first_distributions/Gaussiandistribution.py
my_first_distributions/Generaldistribution.py
my_first_distributions/__init__.py
my_first_distributions.egg-info/PKG-INFO
my_first_distributions.egg-info/SOURCES.txt
my_first_distributions.egg-info/dependency_links.txt
my_first_distributions.egg-info/not-zip-safe
my_first_distributions.egg-info/top_level.txt